telegeo/__init__.py
telegeo/telegeo.py
telegeo/telegeo_notebook.py
telegeo-0.1.2.dist-info/METADATA
telegeo-0.1.2.dist-info/WHEEL
telegeo-0.1.2.dist-info/licenses/LICENSE
telegeo-0.1.2.dist-info/RECORD
