Metadata-Version: 2.1
Name: telegeo
Version: 0.1.2
Summary: This is a python package for scraping Telegram data based on geolocation.
Author-email: Wanjiang Jacob Zhang <zwj1994code@gmail.com>
License: MIT License
Classifier: License :: OSI Approved :: MIT License
Classifier: Operating System :: OS Independent
Classifier: Programming Language :: Python :: 3
Requires-Python: >=3.7
Requires-Dist: geopy
Requires-Dist: pandas
Requires-Dist: plotly
Requires-Dist: telethon
Requires-Dist: tqdm
